xml_python/__init__.py
xml_python-0.4.2.dist-info/AUTHORS
xml_python-0.4.2.dist-info/LICENSE
xml_python-0.4.2.dist-info/METADATA
xml_python-0.4.2.dist-info/WHEEL
xml_python-0.4.2.dist-info/pbr.json
xml_python-0.4.2.dist-info/top_level.txt
xml_python-0.4.2.dist-info/RECORD
