Metadata-Version: 2.1
Name: xml-python
Version: 0.4.2
Summary: Create Python objects from XML using decorated functions to parse the nodes
Home-page: https://github.com/chrisnorman7/xml_objects
Author: Chris Norman
Author-email: chris.norman2@googlemail.com
License: MPL-2
Platform: UNKNOWN
Requires-Dist: attrs
